hello_xin/__init__.py
hello_xin/say_hello.py
hello_xin-1.0.0.dist-info/LICENSE
hello_xin-1.0.0.dist-info/METADATA
hello_xin-1.0.0.dist-info/WHEEL
hello_xin-1.0.0.dist-info/top_level.txt
hello_xin-1.0.0.dist-info/RECORD
